autoant
