Metadata-Version: 1.1
Name: autoant
Version: 0.4.0
Summary: File processing automation
Home-page: https://github.com/dpgaspar/autoant/
Author: Daniel Vaz Gaspar
Author-email: danielvazgaspar@gmail.com
License: BSD
Platform: any
Classifier: Development Status :: 4 - Beta
Classifier: Environment :: Console
Classifier: Intended Audience :: System Administrators
Classifier: License :: OSI Approved :: BSD License
Classifier: Operating System :: OS Independent
Classifier: Programming Language :: Python
Classifier: Topic :: System :: Systems Administration
